LICENSE
README.md
setup.py
distributedlog/__init__.py
distributedlog/logger.py
distributedlog.egg-info/PKG-INFO
distributedlog.egg-info/SOURCES.txt
distributedlog.egg-info/dependency_links.txt
distributedlog.egg-info/top_level.txt